LICENSE.txt
MANIFEST.in
README.rst
setup.py
data/rpi2casterd.conf
data/rpi2casterd.service
rpi2casterd/__init__.py
rpi2casterd/__main__.py
rpi2casterd/main.py
rpi2casterd/smbus.py
rpi2casterd/wiringpi.py
rpi2casterd.egg-info/PKG-INFO
rpi2casterd.egg-info/SOURCES.txt
rpi2casterd.egg-info/dependency_links.txt
rpi2casterd.egg-info/entry_points.txt
rpi2casterd.egg-info/requires.txt
rpi2casterd.egg-info/top_level.txt
rpi2casterd.egg-info/zip-safe