Metadata-Version: 1.1
Name: rpi2casterd
Version: 2.3.1
Summary: Hardware control daemon for rpi2caster
Home-page: http://github.com/elegantandrogyne/rpi2casterd
Author: Christophe Catherine Slychan
Author-email: krzysztof.slychan@gmail.com
License: MIT
Platform: UNKNOWN
Classifier: Development Status :: 5 - Production/Stable
Classifier: Topic :: System :: Hardware :: Hardware Drivers
Classifier: License :: OSI Approved :: MIT License
Classifier: Natural Language :: English
Classifier: Operating System :: POSIX :: Linux
Classifier: Programming Language :: Python :: 3 :: Only
Classifier: Framework :: Flask
